{
  "surveys": [
    {
      "id": "q1",
      "title": "Q1: Feel valued in your job at the moment",
      "csv": "data/q1.csv",
      "answerColumn": "To what extent you feel valued in your job at the moment?",
      "textColumn": "Anything you want to add?"
    },
    {
      "id": "q2",
      "title": "Q2: Confidence in career planning",
      "csv": "data/q2.csv",
      "answerColumn": "How confident do you feel about your career planning?",
      "textColumn": "Anything you want to add?"
    },
    {
      "id": "q3",
      "title": "Q3: Job Description & Day-to-day Work",
      "csv": "data/q3.csv",
      "answerColumn": "To what extent does the information provided during your job interview align with your day-to-day work?",
      "textColumn": "Anything you want to add?"
    }
  ]
}
